jjaljup
