Metadata-Version: 1.1
Name: jjaljup
Version: 0.0.5
Summary: Downloads images in your favorite tweets.
Home-page: https://github.com/clee704/jjaljup
Author: Choongmin Lee
Author-email: choongmin@me.com
License: MIT
Keywords: crawler twitter downloader
Platform: UNKNOWN
Classifier: Development Status :: 3 - Alpha
Classifier: Environment :: Console
Classifier: Intended Audience :: Developers
Classifier: Intended Audience :: End Users/Desktop
Classifier: License :: OSI Approved :: MIT License
Classifier: Natural Language :: Korean
Classifier: Programming Language :: Python :: 2.6
Classifier: Programming Language :: Python :: 2.7
Classifier: Programming Language :: Python :: Implementation :: CPython
Classifier: Topic :: Utilities
